eridu/__init__.py
eridu/config.py
eridu/core.py
eridu/logger.py
sopython_eridu-0.3.0.dist-info/DESCRIPTION.rst
sopython_eridu-0.3.0.dist-info/METADATA
sopython_eridu-0.3.0.dist-info/RECORD
sopython_eridu-0.3.0.dist-info/WHEEL
sopython_eridu-0.3.0.dist-info/entry_points.txt
sopython_eridu-0.3.0.dist-info/metadata.json
sopython_eridu-0.3.0.dist-info/top_level.txt
